{
    "franketienne": [
        {
            "Author": "Frankétienne",
            "Descriptor": "",
            "Genre": "Fiction (Novel)",
            "Language": "English",
            "Pub_id": "brooklyn_ny_united_states",
            "Pubdate": "2014",
            "Publisher": "Archipelago Books",
            "Title": "Ready To Burst",
            "Translation": "y"
        },
        {
            "Author": "Frankétienne",
            "Descriptor": "",
            "Genre": "",
            "Language": "French",
            "Pub_id": "la_roque_d'anthéron_france",
            "Pubdate": "2013",
            "Publisher": "Vents d'ailleurs",
            "Title": "Les Échos De L'abîme",
            "Translation": "n"
        },
        {
            "Author": "Frankétienne",
            "Descriptor": "",
            "Genre": "",
            "Language": "French",
            "Pub_id": "la_roque_d'anthéron_france",
            "Pubdate": "2013",
            "Publisher": "Vents d'ailleurs",
            "Title": "Et La Voyance Explose: Spirale",
            "Translation": "n"
        },
        {
            "Author": "Frankétienne",
            "Descriptor": "",
            "Genre": "Fiction (Novel)",
            "Language": "English",
            "Pub_id": "charlottesville_va_united_states",
            "Pubdate": "2018",
            "Publisher": "University of Virginia Press",
            "Title": "Dezafi",
            "Translation": "y"
        },
        {
            "Author": "Frankétienne",
            "Descriptor": "",
            "Genre": "Fiction (Novel)",
            "Language": "Haitian Creole",
            "Pub_id": "port_au_prince_haiti",
            "Pubdate": "1978",
            "Publisher": "Editions du Soleil",
            "Title": "Pèlin Tèt - Les Émigrès",
            "Translation": "n"
        }
    ],
    "manthony": [
        {
            "Author": "Michael Anthony",
            "Descriptor": "",
            "Genre": "Fiction (Short Story Collection)",
            "Language": "English",
            "Pub_id": "north_devon_england",
            "Pubdate": "1967",
            "Publisher": "Stockwell",
            "Title": "Michael Anthony's Tales for Young and Old",
            "Translation": "n"
        },
        {
            "Author": "Michael Anthony",
            "Descriptor": "",
            "Genre": "Fiction (Novel)",
            "Language": "English",
            "Pub_id": "oxford_england",
            "Pubdate": "1996",
            "Publisher": "Heinemann",
            "Title": "In the Heat of the Day",
            "Translation": "n"
        },
        {
            "Author": "Michael Anthony",
            "Descriptor": "",
            "Genre": "Fiction (Novel)",
            "Language": "English",
            "Pub_id": "oxford_england",
            "Pubdate": "2001",
            "Publisher": "Heinemann",
            "Title": "High Tide of Intrigue",
            "Translation": "n"
        },
        {
            "Author": "Michael Anthony",
            "Descriptor": "",
            "Genre": "Fiction (Short Story Collection)",
            "Language": "English",
            "Pub_id": "kingston_jamaica",
            "Pubdate": "2007",
            "Publisher": "Ian Randle Publishers",
            "Title": "The Chieftain's Carnival and Other Stories",
            "Translation": "n"
        },
        {
            "Author": "Michael Anthony",
            "Descriptor": "",
            "Genre": "Fiction (Novel)",
            "Language": "English",
            "Pub_id": "kingston_jamaica",
            "Pubdate": "2007",
            "Publisher": "Ian Randle Publishers",
            "Title": "Bright Road to El Dorado",
            "Translation": "n"
        },
        {
            "Author": "Michael Anthony",
            "Descriptor": "",
            "Genre": "Fiction (Novel)",
            "Language": "English",
            "Pub_id": "port_of_spain_trinidad",
            "Pubdate": "2014",
            "Publisher": "Heinemann",
            "Title": "Green Days by the River",
            "Translation": "n"
        },
        {
            "Author": "Michael Anthony",
            "Descriptor": "",
            "Genre": "Fiction (Novel)",
            "Language": "English",
            "Pub_id": "london__england",
            "Pubdate": "1967",
            "Publisher": "Heinemann",
            "Title": "Green Days by the River",
            "Translation": "n"
        },
        {
            "Author": "Michael Anthony",
            "Descriptor": "",
            "Genre": "Fiction (Novel)",
            "Language": "English",
            "Pub_id": "london__england",
            "Pubdate": "1963",
            "Publisher": "Heinemann",
            "Title": "Games Were Coming",
            "Translation": "n"
        }
    ],
    "psallfrey": [
        {
            "Author": "Phyllis Shand Allfrey",
            "Descriptor": "",
            "Genre": "Fiction (Novel)",
            "Language": "English",
            "Pub_id": "washington_united_states",
            "Pubdate": "1985",
            "Publisher": "Three Continents",
            "Title": "The Orchid House",
            "Translation": "n"
        },
        {
            "Author": "Phyllis Shand Allfrey",
            "Descriptor": "",
            "Genre": "Fiction (Novel)",
            "Language": "English",
            "Pub_id": "united_kingdom",
            "Pubdate": "1982",
            "Publisher": "Virago Press",
            "Title": "The Orchid House",
            "Translation": "n"
        },
        {
            "Author": "Phyllis Shand Allfrey",
            "Descriptor": "",
            "Genre": "Fiction (Novel)",
            "Language": "Czech",
            "Pub_id": "praha_czech_republic",
            "Pubdate": "1986",
            "Publisher": "Svoboda",
            "Title": "Dum Mezi Orchidejemi",
            "Translation": "y"
        },
        {
            "Author": "Phyllis Shand Allfrey",
            "Descriptor": "",
            "Genre": "Poetry Collection",
            "Language": "English",
            "Pub_id": "trafalgar_dominica",
            "Pubdate": "2012",
            "Publisher": "Papillote Press",
            "Title": "It Falls Into Place",
            "Translation": "n"
        },
        {
            "Author": "Phyllis Shand Allfrey",
            "Descriptor": "",
            "Genre": "Fiction (Novel)",
            "Language": "English",
            "Pub_id": "trafalgar_dominica",
            "Pubdate": "2014",
            "Publisher": "Papillote Press",
            "Title": "Love For An Island: The Collected Poems Of Phyllis Shand Allfrey",
            "Translation": "n"
        },
        {
            "Author": "Phyllis Shand Allfrey",
            "Descriptor": "",
            "Genre": "Fiction (Novel)",
            "Language": "English",
            "Pub_id": "london__england",
            "Pubdate": "1953",
            "Publisher": "Virago Press",
            "Title": "The Orchid House",
            "Translation": "n"
        }
    ],
    "rantoni": [
        {
            "Author": "Robert Antoni",
            "Descriptor": "",
            "Genre": "Fiction (Novel)",
            "Language": "English",
            "Pub_id": "woodstock_ny_united_states",
            "Pubdate": "1992",
            "Publisher": "The Overlook Press",
            "Title": "Divina Trace",
            "Translation": "n"
        },
        {
            "Author": "Robert Antoni",
            "Descriptor": "",
            "Genre": "Fiction (Novel)",
            "Language": "English",
            "Pub_id": "woodstock_ny_united_states",
            "Pubdate": "1993",
            "Publisher": "The Overlook Press",
            "Title": "Divina Trace",
            "Translation": "n"
        },
        {
            "Author": "Robert Antoni",
            "Descriptor": "",
            "Genre": "Fiction (Novel)",
            "Language": "English",
            "Pub_id": "brooklyn_ny_united_states",
            "Pubdate": "2013",
            "Publisher": "Akashic Books",
            "Title": "As Flies to Whatless Boys",
            "Translation": "n"
        },
        {
            "Author": "Robert Antoni",
            "Descriptor": "",
            "Genre": "Fiction (Novel)",
            "Language": "Spanish",
            "Pub_id": "barcelona",
            "Pubdate": "2002",
            "Publisher": "Editorial Anagrama",
            "Title": "Los Cuentos Eróticos de Mi Abuela",
            "Translation": "y"
        },
        {
            "Author": "Robert Antoni",
            "Descriptor": "",
            "Genre": "Anthology",
            "Language": "English",
            "Pub_id": "brooklyn_ny_united_states",
            "Pubdate": "2008",
            "Publisher": "Akashic Books",
            "Title": "Trinidad Noir",
            "Translation": "n"
        }
    ]
}